LinkedLib/DictionaryNode.py
LinkedLib/LinkedDictionary.py
LinkedLib/LinkedList.py
LinkedLib/ListNode.py
LinkedLib/Node.py
LinkedLib/__init__.py
LinkedLib-0.0.6.dist-info/LICENSE
LinkedLib-0.0.6.dist-info/METADATA
LinkedLib-0.0.6.dist-info/WHEEL
LinkedLib-0.0.6.dist-info/top_level.txt
LinkedLib-0.0.6.dist-info/RECORD
