Metadata-Version: 2.1
Name: LinkedLib
Version: 0.0.6
Summary: A python package for utilizing linked datastructures
Author-email: Robert Reynolds <rldr.europa@gmail.com>
Project-URL: Homepage, https://github.com/Robert-DeForrest-Reynolds/LinkedLib
Project-URL: Issues, https://github.com/Robert-DeForrest-Reynolds/LinkedLib/issues
Classifier: Programming Language :: Python :: 3
Classifier: License :: OSI Approved :: MIT License
Classifier: Operating System :: OS Independent
Requires-Python: >=3.11
License-File: LICENSE
